donatello/__init__.py
donatello/async_client.py
donatello/base.py
donatello/client.py
donatello/events.py
donatello/models/__init__.py
donatello/models/client.py
donatello/models/client_list.py
donatello/models/donate.py
donatello/models/donate_list.py
donatello/models/longpool_donale.py
donatello/models/user.py
donatello/models/user_donates.py
donatello_py-1.0.3.dist-info/licenses/LICENSE
donatello_py-1.0.3.dist-info/METADATA
donatello_py-1.0.3.dist-info/WHEEL
donatello_py-1.0.3.dist-info/top_level.txt
donatello_py-1.0.3.dist-info/RECORD
