Metadata-Version: 2.4
Name: donatello-py
Version: 1.0.3
Summary: A asynchronous/synchronous python wrapper for the Donatello API.
Home-page: https://github.com/hampta/donatello-py
Author: hampta
License: MIT
Project-URL: Documentation, https://donatello-py.readthedocs.io/en/latest/
Project-URL: Issue tracker, https://github.com/hampta/donatello-py/issues
Classifier: Development Status :: 5 - Production/Stable
Classifier: License :: OSI Approved :: MIT License
Classifier: Intended Audience :: Developers
Classifier: Natural Language :: English
Classifier: Operating System :: OS Independent
Classifier: Programming Language :: Python :: 3.9
Classifier: Programming Language :: Python :: 3.10
Classifier: Programming Language :: Python :: 3.11
Classifier: Topic :: Internet
Classifier: Topic :: Software Development :: Libraries
Classifier: Topic :: Software Development :: Libraries :: Python Modules
Classifier: Topic :: Utilities
Classifier: Typing :: Typed
Requires-Python: >=3.9.0
License-File: LICENSE
Requires-Dist: pydantic
Requires-Dist: requests
Requires-Dist: aiohttp
Provides-Extra: docs
Requires-Dist: Sphinx==7.2.6; extra == "docs"
Requires-Dist: sphinxcontrib_trio==1.1.2; extra == "docs"
Requires-Dist: sphinxcontrib-websupport; extra == "docs"
Requires-Dist: furo==2023.9.10; extra == "docs"
Requires-Dist: typing-extensions<5,>=4.3; extra == "docs"
Requires-Dist: sphinx_copybutton; extra == "docs"
Provides-Extra: speed
Requires-Dist: ujson>=3.5.4; extra == "speed"
Dynamic: author
Dynamic: classifier
Dynamic: description
Dynamic: description-content-type
Dynamic: home-page
Dynamic: license
Dynamic: license-file
Dynamic: project-url
Dynamic: provides-extra
Dynamic: requires-dist
Dynamic: requires-python
Dynamic: summary
